Day 3/jk_flipflop.v
// jk_flipflop.v
module jk_flipflop (
    input wire j,
    input wire k,
    input wire clk,
    output reg q,
    output wire qn
);

assign qn = ~q;

always @(posedge clk) begin
    case ({j, k})
        2'b00: q <= q;        // No change
        2'b01: q <= 0;        // Reset
        2'b10: q <= 1;        // Set
        2'b11: q <= ~q;       // Toggle
    endcase
end

endmodule

Day 3/tb_jk_flipflop.v
// tb_jk_flipflop.v
`timescale 1ns / 1ps

module tb_jk_flipflop;

    reg j, k, clk;
    wire q, qn;

    // Instantiate the module
    jk_flipflop uut (
        .j(j),
        .k(k),
        .clk(clk),
        .q(q),
        .qn(qn)
    );

    // Clock generation
    always #5 clk = ~clk;

    initial begin
        $dumpfile("jk_flipflop.vcd");
        $dumpvars(0, tb_jk_flipflop);

        $display("Time\tJ\tK\tQ\tQn");
        $monitor("%0dns\t%b\t%b\t%b\t%b", $time, j, k, q, qn);

        // Initial values
        clk = 0; j = 0; k = 0;

        #10 j = 0; k = 1;  // Reset
        #10 j = 1; k = 0;  // Set
        #10 j = 1; k = 1;  // Toggle
        #10 j = 0; k = 0;  // No Change
        #10 j = 1; k = 1;  // Toggle again

        #10 $finish;
    end

endmodule

Day 3/jk_flipflop.vcd
$date
	Wed Apr  9 10:29:10 2025
$end
$version
	Icarus Verilog
$end
$timescale
	1ps
$end
$scope module tb_jk_flipflop $end
$var wire 1 ! qn $end
$var wire 1 " q $end
$var reg 1 # clk $end
$var reg 1 $ j $end
$var reg 1 % k $end
$scope module uut $end
$var wire 1 # clk $end
$var wire 1 $ j $end
$var wire 1 % k $end
$var wire 1 ! qn $end
$var reg 1 " q $end
$upscope $end
$upscope $end
$enddefinitions $end
$comment Show the parameter values. $end
$dumpall
$end
#0
$dumpvars
0%
0$
0#
x"
x!
$end
#5000
1#
#10000
0#
1%
#15000
1!
0"
1#
#20000
0#
0%
1$
#25000
0!
1"
1#
#30000
0#
1%
#35000
1!
0"
1#
#40000
0#
0%
0$
#45000
1#
#50000
0#
1%
1$
#55000
0!
1"
1#
