Day 3/t_flipflop.v
module t_flipflop (
    input wire clk,
    input wire t,
    input wire rst,     // Active-high synchronous reset
    output reg q
);
    always @(posedge clk) begin
        if (rst)
            q <= 0;
        else if (t)
            q <= ~q;    // Toggle
        else
            q <= q;     // Hold
    end
endmodule

Day 3/tb_t_flipflop.v
`timescale 1ns / 1ps

module tb_t_flipflop;

    reg clk;
    reg t;
    reg rst;
    wire q;

    // Instantiate T Flip-Flop
    t_flipflop uut (
        .clk(clk),
        .t(t),
        .rst(rst),
        .q(q)
    );

    // Clock generation: 10ns period
    initial begin
        clk = 0;
        forever #5 clk = ~clk;
    end

    initial begin
        $dumpfile("t_flipflop.vcd"); // For GTKWave
        $dumpvars(0, tb_t_flipflop);

        $display("Time\tclk\tt\trst\tq");
        $monitor("%0dns\t%b\t%b\t%b\t%b", $time, clk, t, rst, q);

        // Simulation sequence
        rst = 1; t = 0; #10;
        rst = 0; t = 1; #20;
        t = 0; #10;
        t = 1; #20;
        t = 0; #10;
        $finish;
    end
endmodule

Day 3/t_flipflop.vcd
$date
	Wed Apr  9 13:04:17 2025
$end
$version
	Icarus Verilog
$end
$timescale
	1ps
$end
$scope module tb_t_flipflop $end
$var wire 1 ! q $end
$var reg 1 " clk $end
$var reg 1 # rst $end
$var reg 1 $ t $end
$scope module uut $end
$var wire 1 " clk $end
$var wire 1 # rst $end
$var wire 1 $ t $end
$var reg 1 ! q $end
$upscope $end
$upscope $end
$enddefinitions $end
$comment Show the parameter values. $end
$dumpall
$end
#0
$dumpvars
0$
1#
0"
x!
$end
#5000
0!
1"
#10000
0"
1$
0#
#15000
1!
1"
#20000
0"
#25000
0!
1"
#30000
0"
0$
#35000
1"
#40000
0"
1$
#45000
1!
1"
#50000
0"
#55000
0!
1"
#60000
0"
0$
