Day4/siso_shift_register.v
module siso_shift_register (
    input clk,
    input rst,
    input serial_in,
    output serial_out
);
    reg [3:0] shift_reg;

    always @(posedge clk or posedge rst) begin
        if (rst)
            shift_reg <= 4'b0000;
        else
            shift_reg <= {shift_reg[2:0], serial_in};
    end

    assign serial_out = shift_reg[3];  // MSB is the serial output
endmodule

Day4/tb_siso_shift_register.v
module tb_siso_shift_register;

    reg clk;
    reg rst;
    reg serial_in;
    wire serial_out;

    siso_shift_register uut (
        .clk(clk),
        .rst(rst),
        .serial_in(serial_in),
        .serial_out(serial_out)
    );

    initial begin
        clk = 0;
        forever #5 clk = ~clk;  // Clock toggles every 5 time units
    end

    initial begin
        $dumpfile("siso.vcd");      // VCD file for waveform
        $dumpvars(0, tb_siso_shift_register);

        rst = 1;
        serial_in = 0;

        #10 rst = 0;

        #10 serial_in = 1;
        #10 serial_in = 0;
        #10 serial_in = 1;
        #10 serial_in = 1;

        #40 $finish;
    end

endmodule

Day4/siso.vcd
$date
	Thu Apr 10 05:02:28 2025
$end
$version
	Icarus Verilog
$end
$timescale
	1s
$end
$scope module tb_siso_shift_register $end
$var wire 1 ! serial_out $end
$var reg 1 " clk $end
$var reg 1 # rst $end
$var reg 1 $ serial_in $end
$scope module uut $end
$var wire 1 " clk $end
$var wire 1 # rst $end
$var wire 1 $ serial_in $end
$var wire 1 ! serial_out $end
$var reg 4 % shift_reg [3:0] $end
$upscope $end
$upscope $end
$enddefinitions $end
$comment Show the parameter values. $end
$dumpall
$end
#0
$dumpvars
b0 %
0$
1#
0"
0!
$end
#5
1"
#10
0"
0#
#15
1"
#20
0"
1$
#25
b1 %
1"
#30
0"
0$
#35
b10 %
1"
#40
0"
1$
#45
b101 %
1"
#50
0"
#55
1!
b1011 %
1"
#60
0"
#65
0!
b111 %
1"
#70
0"
#75
1!
b1111 %
1"
